MANIFEST.in
setup.py
muapi/Auth.py
muapi/Module.py
muapi/Response.py
muapi/Router.py
muapi/__init__.py
muapi/bootstrap.py
muapi/config-default.ini
muapi/config.ini
muapi/configurator.py
muapi/dbConnector.py
muapi/error.py
muapi/geo.py
muapi/role.py
muapi/session.py
muapi/user.py
muapi.egg-info/PKG-INFO
muapi.egg-info/SOURCES.txt
muapi.egg-info/dependency_links.txt
muapi.egg-info/requires.txt
muapi.egg-info/top_level.txt
muapi/modules/__init__.py
muapi/modules/authorization.py
muapi/modules/configuration.py
muapi/modules/users.py
test/test.py