Metadata-Version: 1.1
Name: muapi
Version: 0.1.5
Summary: Modular user-oriented REST API
Home-page: https://github.com/petrstehlik/muapi
Author: Petr Stehlík
Author-email: pe.stehlik@gmail.com
License: UNKNOWN
Download-URL: https://github.com/petrstehlik/muapi/archive/0.1.tar.gz
Keywords: modular,user-oriented,rest,api,flask
Platform: UNKNOWN
